.hgignore
.hgtags
ABOUT.txt
CHANGES.txt
COPYRIGHT.txt
LICENSE.txt
README.txt
bootstrap.py
buildout.cfg
setup.py
tl/__init__.py
tl.buildout_virtual_python.egg-info/PKG-INFO
tl.buildout_virtual_python.egg-info/SOURCES.txt
tl.buildout_virtual_python.egg-info/dependency_links.txt
tl.buildout_virtual_python.egg-info/entry_points.txt
tl.buildout_virtual_python.egg-info/namespace_packages.txt
tl.buildout_virtual_python.egg-info/requires.txt
tl.buildout_virtual_python.egg-info/top_level.txt
tl.buildout_virtual_python.egg-info/zip-safe
tl/buildout_virtual_python/__init__.py
tl/buildout_virtual_python/base.py
tl/buildout_virtual_python/base.txt
tl/buildout_virtual_python/interpreter.txt
tl/buildout_virtual_python/tests/__init__.py
tl/buildout_virtual_python/tests/test_doctests.py