Metadata-Version: 1.0
Name: tl.buildout-virtual-python
Version: 0.2
Summary: zc.buildout recipe for creating a virtual Python installation
Home-page: http://www.thomas-lotze.de/en/software/buildout-recipes/
Author: Thomas Lotze
Author-email: thomas@thomas-lotze.de
License: ZPL 2.1
Keywords: buildout zc.buildout recipe virtual python environment virtualenv
Platform: UNKNOWN
Classifier: Environment :: Console
Classifier: Environment :: Plugins
Classifier: Framework :: Buildout
Classifier: Intended Audience :: Developers
Classifier: Intended Audience :: System Administrators
Classifier: License :: OSI Approved :: Zope Public License
Classifier: Operating System :: OS Independent
Classifier: Programming Language :: Python
Classifier: Programming Language :: Python :: 2
Classifier: Programming Language :: Python :: 2.5
Classifier: Programming Language :: Python :: 2.6
Classifier: Programming Language :: Python :: 2.7
Classifier: Programming Language :: Python :: 2 :: Only
Classifier: Topic :: Software Development :: Build Tools
Classifier: Topic :: System :: Software Distribution
